ydk_models_ietf-0.1.5.post1-nspkg.pth
ydk/models/ietf/__init__.py
ydk/models/ietf/_yang_ns.py
ydk/models/ietf/iana_if_type.py
ydk/models/ietf/ietf_diffserv_action.py
ydk/models/ietf/ietf_diffserv_classifier.py
ydk/models/ietf/ietf_diffserv_policy.py
ydk/models/ietf/ietf_diffserv_target.py
ydk/models/ietf/ietf_event_notifications.py
ydk/models/ietf/ietf_inet_types.py
ydk/models/ietf/ietf_interfaces.py
ydk/models/ietf/ietf_ip.py
ydk/models/ietf/ietf_ipv4_unicast_routing.py
ydk/models/ietf/ietf_ipv6_unicast_routing.py
ydk/models/ietf/ietf_key_chain.py
ydk/models/ietf/ietf_netconf.py
ydk/models/ietf/ietf_netconf_acm.py
ydk/models/ietf/ietf_netconf_monitoring.py
ydk/models/ietf/ietf_netconf_with_defaults.py
ydk/models/ietf/ietf_ospf.py
ydk/models/ietf/ietf_restconf_monitoring.py
ydk/models/ietf/ietf_routing.py
ydk/models/ietf/ietf_syslog_types.py
ydk/models/ietf/ietf_yang_library.py
ydk/models/ietf/ietf_yang_push.py
ydk/models/ietf/ietf_yang_smiv2.py
ydk/models/ietf/policy_types.py
ydk/models/ietf/_yang/iana-crypt-hash.yang
ydk/models/ietf/_yang/iana-if-type.yang
ydk/models/ietf/_yang/ietf-diffserv-action.yang
ydk/models/ietf/_yang/ietf-diffserv-classifier.yang
ydk/models/ietf/_yang/ietf-diffserv-policy.yang
ydk/models/ietf/_yang/ietf-diffserv-target.yang
ydk/models/ietf/_yang/ietf-event-notifications.yang
ydk/models/ietf/_yang/ietf-inet-types.yang
ydk/models/ietf/_yang/ietf-interfaces-ext.yang
ydk/models/ietf/_yang/ietf-interfaces.yang
ydk/models/ietf/_yang/ietf-ip.yang
ydk/models/ietf/_yang/ietf-ipv4-unicast-routing.yang
ydk/models/ietf/_yang/ietf-ipv6-unicast-routing.yang
ydk/models/ietf/_yang/ietf-key-chain.yang
ydk/models/ietf/_yang/ietf-netconf-acm.yang
ydk/models/ietf/_yang/ietf-netconf-monitoring.yang
ydk/models/ietf/_yang/ietf-netconf-notifications.yang
ydk/models/ietf/_yang/ietf-netconf-with-defaults.yang
ydk/models/ietf/_yang/ietf-netconf.yang
ydk/models/ietf/_yang/ietf-ospf.yang
ydk_models_ietf-0.1.5.post1.dist-info/DESCRIPTION.rst
ydk_models_ietf-0.1.5.post1.dist-info/METADATA
ydk_models_ietf-0.1.5.post1.dist-info/RECORD
ydk_models_ietf-0.1.5.post1.dist-info/WHEEL
ydk_models_ietf-0.1.5.post1.dist-info/metadata.json
ydk_models_ietf-0.1.5.post1.dist-info/namespace_packages.txt
ydk_models_ietf-0.1.5.post1.dist-info/top_level.txt
