Metadata-Version: 2.0
Name: ydk-models-ietf
Version: 0.1.5.post1
Summary: YDK bundle for IETF models
Home-page: https://github.com/CiscoDevNet/ydk-py
Author: Cisco Systems
Author-email: yang-dk@cisco.com
License: Apache 2.0
Keywords: yang,C++11,python bindings
Platform: UNKNOWN
Classifier: Development Status :: 3 - Alpha
Classifier: Intended Audience :: Developers
Classifier: Intended Audience :: Education
Classifier: Intended Audience :: Information Technology
Classifier: Intended Audience :: Science/Research
Classifier: Intended Audience :: System Administrators
Classifier: Topic :: Software Development :: Build Tools
Classifier: Topic :: Software Development :: Libraries
Classifier: License :: OSI Approved :: Apache Software License
Classifier: Programming Language :: Python :: 2.7
Classifier: Programming Language :: Python :: 3
Classifier: Programming Language :: Python :: 3.2
Classifier: Programming Language :: Python :: 3.3
Classifier: Programming Language :: Python :: 3.4
Classifier: Programming Language :: Python :: 3.5
Classifier: Programming Language :: C++
Requires-Dist: ydk (>=0.7.2)
